flareverb/__init__.py
flareverb/analysis.py
flareverb/generate.py
flareverb/reverb.py
flareverb/sampling.py
flareverb/utils.py
flareverb/config/config.py
flareverb/data/pyra_materials.json
flareverb-0.0.7.dist-info/METADATA
flareverb-0.0.7.dist-info/WHEEL
flareverb-0.0.7.dist-info/licenses/LICENSE
flareverb-0.0.7.dist-info/RECORD
