Metadata-Version: 2.4
Name: flareverb
Version: 0.0.7
Summary: An Open-Source Library for RIR Synthesis and Analysis in PyTorch based on FLAMO
Project-URL: Homepage, https://github.com/gdalsanto/flare
Project-URL: Issues, https://github.com/gdalsanto/flare/issues
Author-email: Gloria Dal Santo <gloria.dalsanto@aalto.fi>
Maintainer-email: Gloria Dal Santo <gloria.dalsanto@aalto.fi>
License: MIT License
License-File: LICENSE
Keywords: audio signal processing,data augmentation,data generation,reverb
Classifier: License :: OSI Approved :: MIT License
Classifier: Programming Language :: Python :: 3
Requires-Python: >=3.10
Requires-Dist: flamo>=0.2.7
Requires-Dist: pandas
Requires-Dist: pydantic
Requires-Dist: pyyaml
